rekon/__init__.py
rekon/cli.py
rekon/rekon.py
rekon/sample_data/col_mapping.csv
rekon/sample_data/row_mapping.csv
rekon/sample_data/system_1.csv
rekon/sample_data/system_2.csv
rekon-0.1.7.dist-info/METADATA
rekon-0.1.7.dist-info/RECORD
rekon-0.1.7.dist-info/WHEEL
rekon-0.1.7.dist-info/entry_points.txt
rekon-0.1.7.dist-info/top_level.txt
rekon-0.1.7.dist-info/zip-safe
tests/__init__.py
tests/test_rekon.py
