Metadata-Version: 2.1
Name: rekon
Version: 0.1.7
Summary: rekon provides a suite of reconciliation tools for operations and finance
Home-page: https://github.com/rjdscott/rekon
Author: Rob Scott
Author-email: rob@rjdscott.com
License: MIT license
Keywords: rekon
Platform: UNKNOWN
Classifier: Development Status :: 2 - Pre-Alpha
Classifier: Intended Audience :: Developers
Classifier: License :: OSI Approved :: MIT License
Classifier: Natural Language :: English
Classifier: Programming Language :: Python :: 2
Classifier: Programming Language :: Python :: 2.7
Classifier: Programming Language :: Python :: 3
Classifier: Programming Language :: Python :: 3.4
Classifier: Programming Language :: Python :: 3.5
Classifier: Programming Language :: Python :: 3.6
Classifier: Programming Language :: Python :: 3.7
Requires-Dist: Click (>=6.0)
Requires-Dist: pandas
Requires-Dist: Jinja2
Requires-Dist: openpyxl
